{"id":186,"dept":1,"firstname":"Enrico","lastname":"Streich","email":"Vallie30@gmail.com","phone":"1-860-839-4669 x3921","joiningDate":"2012-11-14T00:17:50.354Z","pincode":102737,"eventtime":1662878944113}
{"id":5,"dept":3,"firstname":"Vernon","lastname":"Bartoletti","email":"Waino_Hyatt@yahoo.com","phone":"1-912-394-4280","joiningDate":"2012-04-30T17:49:20.015Z","pincode":182697,"eventtime":1662878944114}
{"id":126,"dept":2,"firstname":"Kade","lastname":"Zulauf","email":"Clemens.Runte@hotmail.com","phone":"748.259.0352 x45182","joiningDate":"2013-07-09T00:16:50.463Z","pincode":132005,"eventtime":1662878944125}
{"id":14,"dept":3,"firstname":"Maribel","lastname":"O'Connell","email":"Adrienne3@hotmail.com","phone":"275-583-5022 x3962","joiningDate":"2014-05-01T22:34:24.844Z","pincode":138507,"eventtime":1662878944136}
{"id":198,"dept":1,"firstname":"Chase","lastname":"Witting","email":"Ralph65@hotmail.com","phone":"(307) 623-4108 x008","joiningDate":"2015-06-20T23:37:24.961Z","pincode":182668,"eventtime":1662878944146}
{"id":1,"dept":3,"firstname":"Eunice","lastname":"Berge","email":"Elza58@hotmail.com","phone":"851.723.9369","joiningDate":"2013-07-13T09:08:51.893Z","pincode":182224,"eventtime":1662878944157}
{"id":16,"dept":3,"firstname":"Jerod","lastname":"Becker","email":"Kamron.Rohan@hotmail.com","phone":"1-725-968-2888 x71421","joiningDate":"2016-04-09T00:24:44.013Z","pincode":131888,"eventtime":1662878944168}
{"id":44,"dept":1,"firstname":"Shad","lastname":"Lesch","email":"Laisha86@yahoo.com","phone":"312-318-4691 x81223","joiningDate":"2015-08-01T02:33:42.016Z","pincode":132654,"eventtime":1662878944179}
{"id":157,"dept":3,"firstname":"Kaylin","lastname":"Rolfson","email":"Fritz.Ryan@hotmail.com","phone":"1-492-298-8536 x3306","joiningDate":"2012-10-27T12:12:08.454Z","pincode":112738,"eventtime":1662878944189}
{"id":194,"dept":1,"firstname":"Keenan","lastname":"Hettinger","email":"Josefa85@yahoo.com","phone":"(334) 325-1869","joiningDate":"2012-03-15T21:07:54.164Z","pincode":130677,"eventtime":1662878944199}
{"id":69,"dept":2,"firstname":"Mauricio","lastname":"Swift","email":"Elroy_Metz@gmail.com","phone":"435-651-8067","joiningDate":"2014-02-03T03:14:49.050Z","pincode":191694,"eventtime":1662878944209}
{"id":156,"dept":3,"firstname":"Emerson","lastname":"Wisoky","email":"Junior_Mayert67@yahoo.com","phone":"(684) 621-0635","joiningDate":"2013-02-26T11:18:50.489Z","pincode":191696,"eventtime":1662878944219}
{"id":135,"dept":3,"firstname":"Vivianne","lastname":"Casper","email":"Nina_Cummerata@yahoo.com","phone":"(690) 810-3520","joiningDate":"2016-06-10T21:03:12.622Z","pincode":157513,"eventtime":1662878944230}
{"id":182,"dept":1,"firstname":"Annette","lastname":"Reichel","email":"Armani59@hotmail.com","phone":"225-729-4618 x074","joiningDate":"2012-05-10T14:33:08.791Z","pincode":136129,"eventtime":1662878944240}
{"id":110,"dept":1,"firstname":"Mark","lastname":"Rice","email":"Alexis_Prosacco@yahoo.com","phone":"1-467-475-8237","joiningDate":"2014-09-15T17:20:41.670Z","pincode":126395,"eventtime":1662878944250}
{"id":179,"dept":1,"firstname":"Makenzie","lastname":"Bailey","email":"Rosalinda_Johnston49@hotmail.com","phone":"1-348-551-8776 x85403","joiningDate":"2013-02-16T02:17:07.034Z","pincode":168050,"eventtime":1662878944260}
{"id":120,"dept":2,"firstname":"Eusebio","lastname":"Monahan","email":"Dino_Mann49@yahoo.com","phone":"(443) 313-0695","joiningDate":"2015-01-01T02:42:50.046Z","pincode":160900,"eventtime":1662878944271}
{"id":192,"dept":3,"firstname":"Dora","lastname":"Kunze","email":"Jacklyn_Runte@hotmail.com","phone":"(440) 364-1876","joiningDate":"2013-08-11T18:04:11.027Z","pincode":198939,"eventtime":1662878944281}
{"id":7,"dept":1,"firstname":"Kelly","lastname":"Torp","email":"Julianne4@yahoo.com","phone":"(951) 747-2646","joiningDate":"2014-11-28T23:10:09.023Z","pincode":181125,"eventtime":1662878944292}
{"id":49,"dept":1,"firstname":"Mayra","lastname":"Jerde","email":"Zane_Pouros4@hotmail.com","phone":"(546) 460-2236 x1682","joiningDate":"2016-03-03T02:18:27.510Z","pincode":171609,"eventtime":1662878944303}
{"id":151,"dept":3,"firstname":"Junior","lastname":"Fay","email":"Gunner_Wehner84@yahoo.com","phone":"784.282.1503 x2994","joiningDate":"2016-02-21T18:39:05.076Z","pincode":152981,"eventtime":1662878944314}
{"id":51,"dept":1,"firstname":"Merle","lastname":"Barton","email":"Favian.OReilly16@gmail.com","phone":"809-634-7329 x1858","joiningDate":"2014-05-23T15:22:44.759Z","pincode":130811,"eventtime":1662878944325}
{"id":131,"dept":3,"firstname":"Makenna","lastname":"Johnson","email":"Annamae.Goodwin@hotmail.com","phone":"208.575.0404 x31631","joiningDate":"2013-06-02T04:08:34.672Z","pincode":139409,"eventtime":1662878944336}
{"id":47,"dept":2,"firstname":"Quincy","lastname":"Skiles","email":"Jaquan_Nicolas@gmail.com","phone":"1-967-996-5641 x70857","joiningDate":"2013-06-24T19:43:55.024Z","pincode":129165,"eventtime":1662878944347}
{"id":101,"dept":2,"firstname":"Irma","lastname":"Hettinger","email":"Fanny.Bogisich43@yahoo.com","phone":"1-447-837-8211","joiningDate":"2016-05-29T03:57:56.102Z","pincode":153148,"eventtime":1662878944357}
{"id":164,"dept":3,"firstname":"Stefanie","lastname":"Haag","email":"Rolando38@yahoo.com","phone":"274-846-6921 x75122","joiningDate":"2014-02-28T10:30:43.724Z","pincode":102319,"eventtime":1662878944368}
{"id":106,"dept":3,"firstname":"Finn","lastname":"Boyle","email":"Giovanny44@yahoo.com","phone":"(213) 927-4422 x52123","joiningDate":"2015-10-18T03:09:00.242Z","pincode":107115,"eventtime":1662878944378}
{"id":171,"dept":1,"firstname":"Adaline","lastname":"Goyette","email":"Stephon.Bins@yahoo.com","phone":"599-873-2972 x221","joiningDate":"2015-10-31T00:19:39.486Z","pincode":141588,"eventtime":1662878944389}
{"id":194,"dept":3,"firstname":"Baby","lastname":"Batz","email":"Amber18@yahoo.com","phone":"904.892.9572 x106","joiningDate":"2012-12-26T00:08:32.592Z","pincode":193506,"eventtime":1662878944399}
{"id":25,"dept":3,"firstname":"Shyann","lastname":"Zulauf","email":"Domenick.Jast@gmail.com","phone":"317-731-9760 x952","joiningDate":"2012-10-19T11:59:14.257Z","pincode":179259,"eventtime":1662878944410}
{"id":45,"dept":1,"firstname":"Neva","lastname":"Konopelski","email":"Aniyah_Kuvalis21@hotmail.com","phone":"718-201-9339 x16421","joiningDate":"2013-10-19T12:15:25.432Z","pincode":165144,"eventtime":1662878944420}
{"id":170,"dept":2,"firstname":"Jessica","lastname":"Schumm","email":"General.Glover@hotmail.com","phone":"993.484.7065 x33000","joiningDate":"2013-07-05T01:35:14.650Z","pincode":159554,"eventtime":1662878944430}
{"id":87,"dept":3,"firstname":"Jaleel","lastname":"Blanda","email":"Amanda.Hermann87@gmail.com","phone":"380-662-9489","joiningDate":"2013-04-13T11:50:44.338Z","pincode":138763,"eventtime":1662878944441}
{"id":153,"dept":2,"firstname":"Chanelle","lastname":"Ziemann","email":"Felicita_Koch65@gmail.com","phone":"1-961-572-7321 x96747","joiningDate":"2016-12-11T06:23:23.840Z","pincode":196816,"eventtime":1662878944452}
{"id":23,"dept":2,"firstname":"Jimmy","lastname":"Kuphal","email":"Luciano_Goodwin64@hotmail.com","phone":"378-555-7110","joiningDate":"2013-01-25T22:07:21.145Z","pincode":135282,"eventtime":1662878944463}
{"id":74,"dept":1,"firstname":"Antoinette","lastname":"Lemke","email":"Edyth_Grant@gmail.com","phone":"612.343.0125","joiningDate":"2012-01-13T16:19:08.016Z","pincode":137489,"eventtime":1662878944474}
{"id":146,"dept":1,"firstname":"Mariane","lastname":"Ernser","email":"Kirsten_Kessler96@yahoo.com","phone":"835-727-0795","joiningDate":"2014-12-30T21:26:49.891Z","pincode":189632,"eventtime":1662878944484}
{"id":38,"dept":3,"firstname":"Rozella","lastname":"Pouros","email":"Corrine.OConnell51@hotmail.com","phone":"(294) 755-8394","joiningDate":"2015-08-30T18:28:40.543Z","pincode":140017,"eventtime":1662878944495}
{"id":192,"dept":1,"firstname":"Madge","lastname":"Vandervort","email":"Cecilia64@hotmail.com","phone":"1-367-591-2407 x38958","joiningDate":"2015-01-26T22:36:55.544Z","pincode":125268,"eventtime":1662878944506}
{"id":157,"dept":3,"firstname":"Sydney","lastname":"Steuber","email":"Briana.Runolfsson88@hotmail.com","phone":"285.832.9492 x51663","joiningDate":"2015-07-17T22:33:43.190Z","pincode":144448,"eventtime":1662878944517}
{"id":45,"dept":3,"firstname":"Ophelia","lastname":"Quitzon","email":"Teagan_Bernier83@yahoo.com","phone":"1-689-413-6828 x73786","joiningDate":"2015-11-18T08:33:54.582Z","pincode":109387,"eventtime":1662878944528}
{"id":5,"dept":3,"firstname":"Dessie","lastname":"Gerhold","email":"Alessia29@hotmail.com","phone":"(817) 966-8222","joiningDate":"2012-07-30T07:27:54.396Z","pincode":170695,"eventtime":1662878944538}
{"id":43,"dept":3,"firstname":"Joelle","lastname":"Bogisich","email":"Josie47@yahoo.com","phone":"636.652.0758","joiningDate":"2014-10-04T01:27:22.006Z","pincode":150823,"eventtime":1662878944548}
{"id":199,"dept":2,"firstname":"Weston","lastname":"Corkery","email":"Morgan_Durgan@yahoo.com","phone":"1-669-911-7214","joiningDate":"2016-02-20T14:32:47.676Z","pincode":139125,"eventtime":1662878944559}
{"id":169,"dept":3,"firstname":"Devin","lastname":"Barrows","email":"Constance_Haag@hotmail.com","phone":"777.220.0668 x11884","joiningDate":"2012-09-28T19:08:46.333Z","pincode":110069,"eventtime":1662878944569}
{"id":87,"dept":3,"firstname":"Joshuah","lastname":"Padberg","email":"Maryam_Davis26@hotmail.com","phone":"842-377-6116","joiningDate":"2016-11-01T04:40:24.723Z","pincode":137617,"eventtime":1662878944579}
{"id":25,"dept":3,"firstname":"Cheyenne","lastname":"Gorczany","email":"Clovis46@hotmail.com","phone":"901-400-9999 x8351","joiningDate":"2016-08-24T16:03:43.962Z","pincode":127671,"eventtime":1662878944589}
{"id":161,"dept":3,"firstname":"Eldridge","lastname":"Homenick","email":"Carmen.Gaylord@gmail.com","phone":"1-573-558-7017 x1424","joiningDate":"2012-12-11T16:04:19.107Z","pincode":193285,"eventtime":1662878944600}
{"id":187,"dept":1,"firstname":"Kane","lastname":"Harvey","email":"Bradley29@yahoo.com","phone":"229.886.8172 x548","joiningDate":"2013-11-17T02:32:59.944Z","pincode":143420,"eventtime":1662878944611}
{"id":128,"dept":1,"firstname":"Rigoberto","lastname":"Jenkins","email":"Luis_Dicki2@yahoo.com","phone":"241.845.4054","joiningDate":"2012-05-22T06:36:43.116Z","pincode":155685,"eventtime":1662878944622}
{"id":154,"dept":3,"firstname":"Anais","lastname":"Hoppe","email":"Melisa_Hagenes59@hotmail.com","phone":"1-781-216-4410","joiningDate":"2012-01-03T02:34:56.458Z","pincode":152653,"eventtime":1662878944633}
{"id":83,"dept":1,"firstname":"Rigoberto","lastname":"Ferry","email":"Al_Effertz69@gmail.com","phone":"(381) 866-8983","joiningDate":"2014-12-03T22:45:36.374Z","pincode":135073,"eventtime":1662878944643}
{"id":37,"dept":1,"firstname":"Esta","lastname":"Lehner","email":"Lurline_Waters59@hotmail.com","phone":"1-203-205-0773","joiningDate":"2016-10-13T21:25:31.754Z","pincode":133687,"eventtime":1662878944654}
{"id":142,"dept":2,"firstname":"Shayna","lastname":"O'Conner","email":"Luciano.Schmitt9@hotmail.com","phone":"1-457-606-9173 x68354","joiningDate":"2012-09-03T02:00:58.439Z","pincode":147330,"eventtime":1662878944665}
{"id":8,"dept":3,"firstname":"Consuelo","lastname":"Lueilwitz","email":"Cary_Reynolds@gmail.com","phone":"1-701-417-1078 x944","joiningDate":"2015-04-04T11:36:10.189Z","pincode":174918,"eventtime":1662878944676}
{"id":7,"dept":3,"firstname":"Marisa","lastname":"D'Amore","email":"Arely.Frami@yahoo.com","phone":"436-725-9169 x529","joiningDate":"2012-08-18T16:24:44.157Z","pincode":179418,"eventtime":1662878944687}
{"id":18,"dept":1,"firstname":"Tatyana","lastname":"Conroy","email":"Torey.Willms85@gmail.com","phone":"316.903.9204 x41494","joiningDate":"2012-01-09T08:33:33.186Z","pincode":189165,"eventtime":1662878944698}
{"id":119,"dept":2,"firstname":"Zoey","lastname":"Gleason","email":"Moshe_Lang@yahoo.com","phone":"586-512-2162 x9732","joiningDate":"2014-10-20T21:03:18.412Z","pincode":144182,"eventtime":1662878944708}
{"id":113,"dept":3,"firstname":"Mallie","lastname":"Harris","email":"Maverick59@hotmail.com","phone":"414.249.2086","joiningDate":"2012-12-09T00:40:32.954Z","pincode":104677,"eventtime":1662878944718}
{"id":93,"dept":1,"firstname":"Reginald","lastname":"O'Conner","email":"Willard45@yahoo.com","phone":"824-539-3101","joiningDate":"2016-04-06T12:23:02.718Z","pincode":126881,"eventtime":1662878944729}
{"id":73,"dept":1,"firstname":"Jack","lastname":"Zboncak","email":"Christina56@hotmail.com","phone":"871-209-4749","joiningDate":"2015-07-15T12:18:18.310Z","pincode":183038,"eventtime":1662878944739}
{"id":121,"dept":3,"firstname":"Terrill","lastname":"Lind","email":"Elody_Bechtelar@hotmail.com","phone":"(896) 745-2487","joiningDate":"2014-02-10T07:02:16.045Z","pincode":151335,"eventtime":1662878944750}
{"id":143,"dept":1,"firstname":"Lelah","lastname":"D'Amore","email":"Cleora44@hotmail.com","phone":"741.366.5689 x87206","joiningDate":"2014-02-23T20:02:56.548Z","pincode":133519,"eventtime":1662878944760}
{"id":143,"dept":1,"firstname":"Melissa","lastname":"Bayer","email":"Jacinto77@gmail.com","phone":"(909) 591-8608","joiningDate":"2015-05-19T20:14:22.026Z","pincode":112045,"eventtime":1662878944771}
{"id":162,"dept":3,"firstname":"Adolf","lastname":"Pagac","email":"Theresia93@hotmail.com","phone":"1-525-330-7310","joiningDate":"2012-04-10T09:10:56.252Z","pincode":123217,"eventtime":1662878944782}
{"id":183,"dept":2,"firstname":"Rollin","lastname":"Oberbrunner","email":"Erika_Sawayn89@hotmail.com","phone":"1-887-290-3079 x72196","joiningDate":"2016-08-06T12:36:52.837Z","pincode":104726,"eventtime":1662878944793}
{"id":185,"dept":3,"firstname":"Vada","lastname":"Grady","email":"Shaniya64@gmail.com","phone":"1-978-452-8271 x71351","joiningDate":"2016-02-25T11:16:19.630Z","pincode":190917,"eventtime":1662878944804}
{"id":113,"dept":2,"firstname":"Vivianne","lastname":"Bahringer","email":"Adolfo30@yahoo.com","phone":"910-814-9486","joiningDate":"2016-03-04T04:22:58.047Z","pincode":184003,"eventtime":1662878944815}
{"id":4,"dept":1,"firstname":"Geovanny","lastname":"McClure","email":"Jarrod36@gmail.com","phone":"(387) 897-3175","joiningDate":"2014-09-10T02:32:22.443Z","pincode":119636,"eventtime":1662878944825}
{"id":10,"dept":1,"firstname":"Gunnar","lastname":"Mohr","email":"Annette_Greenfelder@gmail.com","phone":"(797) 828-3019 x522","joiningDate":"2013-02-07T10:28:03.856Z","pincode":129747,"eventtime":1662878944835}
{"id":69,"dept":3,"firstname":"Otis","lastname":"Mitchell","email":"Raheem_Durgan62@hotmail.com","phone":"701-427-8923 x22978","joiningDate":"2012-08-18T05:11:38.569Z","pincode":181553,"eventtime":1662878944845}
{"id":168,"dept":2,"firstname":"Oliver","lastname":"Haley","email":"Burnice.Oberbrunner75@yahoo.com","phone":"596-696-1036 x856","joiningDate":"2013-12-06T16:19:03.411Z","pincode":139151,"eventtime":1662878944855}
{"id":83,"dept":1,"firstname":"Karlie","lastname":"Pfannerstill","email":"Alysson68@gmail.com","phone":"913.611.1113 x163","joiningDate":"2014-06-11T14:02:56.086Z","pincode":141555,"eventtime":1662878944866}
{"id":78,"dept":3,"firstname":"Jolie","lastname":"Walter","email":"Estell_Kreiger@yahoo.com","phone":"467.213.7770 x66611","joiningDate":"2012-07-06T20:43:46.396Z","pincode":120659,"eventtime":1662878944877}
{"id":138,"dept":3,"firstname":"Brenden","lastname":"Cronin","email":"Sallie_Casper@hotmail.com","phone":"1-961-653-3134 x237","joiningDate":"2013-07-24T02:48:31.062Z","pincode":165191,"eventtime":1662878944888}
{"id":109,"dept":1,"firstname":"Melisa","lastname":"Mayer","email":"Unique.Olson56@hotmail.com","phone":"534-654-4846","joiningDate":"2015-08-06T12:00:03.847Z","pincode":102326,"eventtime":1662878944902}
{"id":16,"dept":1,"firstname":"Clare","lastname":"Rolfson","email":"Karen.Pouros@gmail.com","phone":"1-653-616-9258 x211","joiningDate":"2015-08-11T03:36:07.834Z","pincode":198057,"eventtime":1662878944909}
{"id":176,"dept":1,"firstname":"Marcelina","lastname":"Nikolaus","email":"Christine.Rodriguez36@gmail.com","phone":"208.553.4096 x30120","joiningDate":"2014-05-06T05:55:57.524Z","pincode":194401,"eventtime":1662878944920}
{"id":164,"dept":1,"firstname":"Janie","lastname":"Hudson","email":"Laurine_Stracke@gmail.com","phone":"775-717-0413","joiningDate":"2016-10-11T05:13:42.366Z","pincode":195480,"eventtime":1662878944930}
{"id":24,"dept":2,"firstname":"Jovanny","lastname":"Wyman","email":"Ulises_Moore@yahoo.com","phone":"(569) 330-8883","joiningDate":"2015-05-11T03:40:49.465Z","pincode":192295,"eventtime":1662878944941}
{"id":148,"dept":1,"firstname":"Domingo","lastname":"Lynch","email":"Milo_Jenkins@hotmail.com","phone":"(507) 745-6876 x6720","joiningDate":"2013-05-16T22:53:20.859Z","pincode":194079,"eventtime":1662878944952}
{"id":92,"dept":3,"firstname":"Cristian","lastname":"Daugherty","email":"Sunny25@hotmail.com","phone":"1-640-205-9067","joiningDate":"2015-01-04T15:03:42.074Z","pincode":115096,"eventtime":1662878944963}
{"id":5,"dept":1,"firstname":"Juanita","lastname":"Hane","email":"Jayme58@yahoo.com","phone":"(203) 229-6653 x763","joiningDate":"2015-11-26T19:55:35.029Z","pincode":118794,"eventtime":1662878944974}
{"id":170,"dept":2,"firstname":"Larissa","lastname":"Balistreri","email":"Oscar_Ritchie76@gmail.com","phone":"830.823.2921 x7714","joiningDate":"2015-07-25T04:08:59.116Z","pincode":180940,"eventtime":1662878944984}
{"id":36,"dept":2,"firstname":"Brandt","lastname":"Hammes","email":"Norbert.Schmidt@hotmail.com","phone":"(427) 322-9770","joiningDate":"2016-10-20T03:22:15.186Z","pincode":152658,"eventtime":1662878944994}
{"id":146,"dept":3,"firstname":"Dorris","lastname":"Mayert","email":"Ezequiel.Sauer79@hotmail.com","phone":"(469) 932-5321 x74201","joiningDate":"2012-07-01T06:08:18.723Z","pincode":132442,"eventtime":1662878945004}
{"id":32,"dept":2,"firstname":"June","lastname":"Bosco","email":"Tess_McLaughlin@gmail.com","phone":"758.219.6488 x13008","joiningDate":"2016-03-10T14:28:25.463Z","pincode":195289,"eventtime":1662878945014}
{"id":152,"dept":3,"firstname":"Kelley","lastname":"Balistreri","email":"Deven72@yahoo.com","phone":"1-700-494-4905 x9232","joiningDate":"2012-07-11T15:26:36.652Z","pincode":142417,"eventtime":1662878945024}
{"id":84,"dept":3,"firstname":"D'angelo","lastname":"Sauer","email":"Sydni.Lind20@gmail.com","phone":"232.659.8442 x217","joiningDate":"2015-10-20T18:36:42.935Z","pincode":175171,"eventtime":1662878945035}
{"id":143,"dept":2,"firstname":"Christian","lastname":"Rohan","email":"Lexie12@yahoo.com","phone":"(328) 534-2323","joiningDate":"2014-05-12T09:17:05.679Z","pincode":198031,"eventtime":1662878945046}
{"id":169,"dept":1,"firstname":"Suzanne","lastname":"Schoen","email":"Jay.Waelchi55@hotmail.com","phone":"(848) 961-1241","joiningDate":"2012-07-15T02:48:36.842Z","pincode":113107,"eventtime":1662878945057}
{"id":179,"dept":3,"firstname":"Cristopher","lastname":"Carter","email":"Brook.Schultz32@gmail.com","phone":"1-871-529-9177 x880","joiningDate":"2012-08-25T16:40:33.318Z","pincode":142153,"eventtime":1662878945068}
{"id":170,"dept":2,"firstname":"Terrence","lastname":"Becker","email":"Sheila_Spinka@hotmail.com","phone":"792.808.3080 x261","joiningDate":"2015-05-21T07:47:05.111Z","pincode":118886,"eventtime":1662878945079}
{"id":198,"dept":1,"firstname":"Randi","lastname":"Kunze","email":"Graciela.Leuschke@hotmail.com","phone":"372-420-7983 x118","joiningDate":"2012-06-22T10:11:03.869Z","pincode":176070,"eventtime":1662878945089}
{"id":106,"dept":2,"firstname":"Marlon","lastname":"Stracke","email":"Logan.Larkin64@gmail.com","phone":"(816) 217-2354","joiningDate":"2013-11-03T17:06:08.780Z","pincode":107311,"eventtime":1662878945100}
{"id":50,"dept":2,"firstname":"Jarrell","lastname":"Roberts","email":"Vivianne_Altenwerth4@hotmail.com","phone":"1-911-722-9713 x7149","joiningDate":"2015-04-10T05:14:58.099Z","pincode":185484,"eventtime":1662878945111}
{"id":50,"dept":1,"firstname":"Alverta","lastname":"Glover","email":"Jeffery.Turner@yahoo.com","phone":"486.527.5608 x4431","joiningDate":"2014-03-04T13:58:56.223Z","pincode":115811,"eventtime":1662878945122}
{"id":46,"dept":1,"firstname":"Ivah","lastname":"Krajcik","email":"Garth.Bahringer43@yahoo.com","phone":"690-516-7687 x25853","joiningDate":"2014-10-25T05:20:38.891Z","pincode":195781,"eventtime":1662878945133}
{"id":188,"dept":1,"firstname":"Camron","lastname":"Oberbrunner","email":"Sydni_Bogan37@yahoo.com","phone":"891-478-4947 x1949","joiningDate":"2012-12-10T20:53:24.874Z","pincode":122679,"eventtime":1662878945144}
{"id":179,"dept":1,"firstname":"Haven","lastname":"Krajcik","email":"Jewell_Lowe28@gmail.com","phone":"1-586-647-2551 x6422","joiningDate":"2014-06-05T10:30:45.744Z","pincode":190794,"eventtime":1662878945154}
